{
  "address": "Xã Hạ Lễ, Huyện Ân Thi, Tỉnh Hưng Yên",
  "ellapsedInMs": 6466,
  "estimatedCost": 0.0037482999999999995,
  "thought": "**Determining the New Administrative Unit for \"Xã Hạ Lễ, Huyện Ân Thi, Tỉnh Hưng Yên\"**\n\nOkay, here's my thought process on this one. The user needs to know the current administrative unit for \"Xã Hạ Lễ, Huyện Ân Thi, Tỉnh Hưng Yên,\" so I need to piece together the changes. First, I have to make sure \"Tỉnh Hưng Yên\" itself hasn't been merged, and I know from the data I have that it hasn't - it remains \"Tỉnh Hưng Yên.\"\n\nNext, I'm diving into the resolutions concerning ward-level changes within \"Tỉnh Hưng Yên.\" I need to find something that specifically mentions \"Xã Hạ Lễ\" or even \"Huyện Ân Thi,\" which should give me a solid clue. I found \"1666/NQ-UBTVQH15,\" and after examining it closely, I hit the jackpot! Section 17 of that resolution explicitly states that \"Xã Hạ Lễ\" is merged into a new unit called \"Xã Hồng Quang.\"\n\nBingo! That's a direct mapping. It also mentions other merging within the \"Huyện Ân Thi\" district like \"Bắc Sơn\" into \"Phạm Ngũ Lão\".\n\nNow that I have the new ward name, \"Xã Hồng Quang,\" I need to confirm its details. I'll search the `New wards` list and, sure enough, I find it with its corresponding code: `{\"ward_code\":\"12196\",\"ward_name\":\"Xã Hồng Quang\",\"province_name\":\"Tỉnh Hưng Yên\"}`.\n\nSince the resolution provides a clear and direct mapping from \"Xã Hạ Lễ\" to \"Xã Hồng Quang,\" my confidence in this answer is high.  That's my final answer.\n",
  "result": [
    {
      "citation": {
        "header": "1666/NQ-UBTVQH15: Sắp xếp các đơn vị hành chính cấp xã của tỉnh Hưng Yên",
        "line": "17. Sắp xếp toàn bộ diện tích tự nhiên, quy mô dân số của các xã Hồ Tùng Mậu, Tiền Phong, Hạ Lễ và Hồng Quang thành xã mới có tên gọi là xã Hồng Quang."
      },
      "confidence": "high",
      "province_name": "Tỉnh Hưng Yên",
      "ward_code": "12196",
      "ward_name": "Xã Hồng Quang"
    }
  ]
}